OpenGL_accelerate/__init__.py
OpenGL_accelerate/arraydatatype.cpython-38-x86_64-linux-gnu.so
OpenGL_accelerate/buffers_formathandler.cpython-38-x86_64-linux-gnu.so
OpenGL_accelerate/errorchecker.cpython-38-x86_64-linux-gnu.so
OpenGL_accelerate/formathandler.cpython-38-x86_64-linux-gnu.so
OpenGL_accelerate/formathandler.pxd
OpenGL_accelerate/latebind.cpython-38-x86_64-linux-gnu.so
OpenGL_accelerate/nones_formathandler.cpython-38-x86_64-linux-gnu.so
OpenGL_accelerate/numpy_formathandler.cpython-38-x86_64-linux-gnu.so
OpenGL_accelerate/vbo.cpython-38-x86_64-linux-gnu.so
OpenGL_accelerate/wrapper.cpython-38-x86_64-linux-gnu.so
OpenGL_accelerate/wrapper.pxd
pyopengl_accelerate-3.1.10.dist-info/METADATA
pyopengl_accelerate-3.1.10.dist-info/WHEEL
pyopengl_accelerate-3.1.10.dist-info/top_level.txt
pyopengl_accelerate-3.1.10.dist-info/RECORD
