Metadata-Version: 2.1
Name: PyOpenGL-accelerate
Version: 3.1.10
Summary: Cython-coded accelerators for PyOpenGL
Home-page: http://pyopengl.sourceforge.net
Download-URL: http://sourceforge.net/project/showfiles.php?group_id=5988
Author: Mike C. Fletcher
Author-email: "Mike C. Fletcher" <mcfletch@vrplumber.com>
License: NOTE:
Project-URL: Homepage, https://mcfletch.github.io/pyopengl/
Project-URL: Download, https://pypi.org/project/PyOpenGL-accelerate/
Project-URL: Source, https://github.com/mcfletch/pyopengl
Project-URL: Documentation, https://mcfletch.github.io/pyopengl/documentation/index.html
Keywords: Graphics,3D,OpenGL,GLU,GLUT,GLE,GLX,EXT,ARB,Mesa,PyOpenGL
Platform: Win32
Platform: Linux
Platform: OS-X
Platform: Posix
Classifier: License :: OSI Approved :: BSD License
Classifier: Programming Language :: Python
Classifier: Programming Language :: Python :: 2
Classifier: Programming Language :: Python :: 3
Classifier: Topic :: Multimedia :: Graphics :: 3D Rendering
Classifier: Topic :: Software Development :: Libraries :: Python Modules
Classifier: Intended Audience :: Developers
